odoo/addons/stock_quant_available_quantity/README.rst
odoo/addons/stock_quant_available_quantity/__init__.py
odoo/addons/stock_quant_available_quantity/__manifest__.py
odoo/addons/stock_quant_available_quantity/i18n/it.po
odoo/addons/stock_quant_available_quantity/i18n/stock_quant_available_quantity.pot
odoo/addons/stock_quant_available_quantity/readme/CONTRIBUTORS.md
odoo/addons/stock_quant_available_quantity/readme/DESCRIPTION.md
odoo/addons/stock_quant_available_quantity/readme/USAGE.md
odoo/addons/stock_quant_available_quantity/static/description/icon.png
odoo/addons/stock_quant_available_quantity/static/description/icon.svg
odoo/addons/stock_quant_available_quantity/static/description/index.html
odoo/addons/stock_quant_available_quantity/views/stock_quant_views.xml
odoo_addon_stock_quant_available_quantity-17.0.1.0.0.2.dist-info/METADATA
odoo_addon_stock_quant_available_quantity-17.0.1.0.0.2.dist-info/WHEEL
odoo_addon_stock_quant_available_quantity-17.0.1.0.0.2.dist-info/top_level.txt
odoo_addon_stock_quant_available_quantity-17.0.1.0.0.2.dist-info/RECORD
